[{
    "name": "Aimee Trettel",
    "address": "123 Home",
    "city": "Haymarket",
    "state": "VA",
    "email": "a@t.com",
    "url": null,
    "likes": "students & atmosphere",
    "interested": "other",
    "rating": "Likely",
    "comments": null,
    "sid": 992518,
    "zip": 20169,
    "phone": 5715559086,
    "date": "2020-05-11",
    "graduation": "May 2020"
  },
  {
    "name": "Betty Boop",
    "address": "123 Betty",
    "city": "Boopville",
    "state": "VA",
    "email": "b@b.com",
    "url": null,
    "likes": "students & location & campus",
    "interested": "friends",
    "rating": "Very Likely",
    "comments": null,
    "sid": 12345678,
    "zip": 20169,
    "phone": 6185551451,
    "date": "2020-03-11",
    "graduation": "May 2020"
  },
  {
    "name": "Calvin Coolidge",
    "address": "123 Cool",
    "city": "Calville",
    "state": "CA",
    "email": "c@c.com",
    "url": null,
    "likes": "students & campus",
    "interested": "Internet",
    "rating": "Unlikely",
    "comments": null,
    "sid": 98765432,
    "zip": 20169,
    "phone": 5553440987,
    "date": "2020-06-11",
    "graduation": "December 2020"
  },
  {
    "name": "Devon DaVinci",
    "address": "123 Picasso",
    "city": "Gogh",
    "state": "VA",
    "email": "d@d.com",
    "url": null,
    "likes": "location & sports",
    "interested": "friends",
    "rating": "Very Likely",
    "comments": "Hello and goodbye",
    "sid": 54763298,
    "zip": 20169,
    "phone": 9994442233,
    "date": "2020-05-04",
    "graduation": "April 2020"
  }
]
